{
  "iconDefinitions": {
    "roadmap": {
      "iconPath": "./icons/roadmap.svg"
    },
    "lock": {
      "iconPath": "./icons/lock.svg"
    },
    "renovate": {
      "iconPath": "./icons/renovate.svg"
    },
    "capacitor": {
      "iconPath": "./icons/capacitor.svg"
    },
    "karma": {
      "iconPath": "./icons/karma.svg"
    },
    "vercel": {
      "iconPath": "./icons/vercel.svg"
    },
    "jsconfig": {
      "iconPath": "./icons/jsconfig.svg"
    },
    "asciidoc": {
      "iconPath": "./icons/asciidoc.svg"
    },
    "svgo": {
      "iconPath": "./icons/svgo.svg"
    },
    "globe": {
      "iconPath": "./icons/globe.svg"
    },
    "nodemon": {
      "iconPath": "./icons/nodemon.svg"
    },
    "blade": {
      "iconPath": "./icons/blade.svg"
    },
    "tsconfig": {
      "iconPath": "./icons/tsconfig.svg"
    },
    "test-ts": {
      "iconPath": "./icons/test-ts.svg"
    },
    "test-js": {
      "iconPath": "./icons/test-js.svg"
    },
    "test-jsx": {
      "iconPath": "./icons/test-jsx.svg"
    },
    "certificate": { "iconPath": "./icons/certificate.svg" },
    "coldfusion": {
      "iconPath": "./icons/coldfusion.svg"
    },
    "lib": {
      "iconPath": "./icons/lib.svg"
    },
    "shader": {
      "iconPath": "./icons/shader.svg"
    },
    "file_text": {
      "iconPath": "./icons/text_dark.svg"
    },
    "file_kotlin": {
      "iconPath": "./icons/kotlin_dark.svg"
    },
    "folder": {
      "iconPath": "./icons/folder_dark.svg"
    },
    "folder_open": {
      "iconPath": "./icons/folder_open_dark.svg"
    },
    "file_ignored": {
      "iconPath": "./icons/ignored_dark.svg"
    },
    "file_css": {
      "iconPath": "./icons/css.svg"
    },
    "file_erb": {
      "iconPath": "./icons/erbFile_dark.svg"
    },
    "file_scss": {
      "iconPath": "./icons/scss.svg"
    },
    "file_json": {
      "iconPath": "./icons/json_dark.svg"
    },
    "file_html": {
      "iconPath": "./icons/html_dark.svg"
    },
    "file_react": {
      "iconPath": "./icons/react_dark.svg"
    },
    "file_ruby": {
      "iconPath": "./icons/dark_ruby.svg"
    },
    "file_rake": {
      "iconPath": "./icons/rakeTask_dark.svg"
    },
    "file_gemfile": {
      "iconPath": "./icons/rubyGems_dark.svg"
    },
    "file_less": {
      "iconPath": "./icons/less_dark.svg"
    },
    "file_javascript": {
      "iconPath": "./icons/javaScript_dark.svg"
    },
    "file_typescript": {
      "iconPath": "./icons/typeScript_dark.svg"
    },
    "file_csv": {
      "iconPath": "./icons/csv_dark.svg"
    },
    "file_vue": {
      "iconPath": "./icons/vueJs.svg"
    },
    "file_editorconfig": {
      "iconPath": "./icons/editorConfig_dark.svg"
    },
    "file_image": {
      "iconPath": "./icons/image_dark.svg"
    },
    "file_font": {
      "iconPath": "./icons/font_dark.svg"
    },
    "file_yaml": {
      "iconPath": "./icons/yaml_dark.svg"
    },
    "file_java": {
      "iconPath": "./icons/java_dark.svg"
    },
    "file_xml": {
      "iconPath": "./icons/xml_dark.svg"
    },
    "file_sql": {
      "iconPath": "./icons/sql_dark.svg"
    },
    "file_slim": {
      "iconPath": "./icons/slim_dark.svg"
    },
    "file_yarn": {
      "iconPath": "./icons/yarn.svg"
    },
    "file_markdown": {
      "iconPath": "./icons/markdown_dark.svg"
    },
    "file_gitignore": {
      "iconPath": "./icons/gitignore.svg"
    },
    "file_properties": {
      "iconPath": "./icons/properties_dark.svg"
    },
    "file_shell": {
      "iconPath": "./icons/shell_dark.svg"
    },
    "file_h": {
      "iconPath": "./icons/h_dark.svg"
    },
    "file_c": {
      "iconPath": "./icons/c_dark.svg"
    },
    "file_cpp": {
      "iconPath": "./icons/cpp_dark.svg"
    },
    "file_scala": {
      "iconPath": "./icons/scala_dark.svg"
    },
    "file_archive": {
      "iconPath": "./icons/archive_dark.svg"
    },
    "file_toml": {
      "iconPath": "./icons/toml_dark.svg"
    },
    "file_python": {
      "iconPath": "./icons/python.svg"
    },
    "file_terraform": {
      "iconPath": "./icons/terraform_dark.svg"
    },
    "file_go": {
      "iconPath": "./icons/go_dark.svg"
    },
    "file_http": {
      "iconPath": "./icons/http_dark.svg"
    },
    "file_docker": {
      "iconPath": "./icons/docker_dark.svg"
    },
    "file_actionscript": {
      "iconPath": "./icons/actionScript_dark.svg"
    },
    "file_php": {
      "iconPath": "./icons/php_dark.svg"
    },
    "file_makefile": {
      "iconPath": "./icons/makefile_dark.svg"
    },
    "file_config": {
      "iconPath": "./icons/config_dark.svg"
    },
    "file_any": {
      "iconPath": "./icons/anyType_dark.svg"
    },
    "file_svelte": {
      "iconPath": "./icons/svelte.svg"
    },
    "file_rust": {
      "iconPath": "./icons/rustFile_dark.svg"
    },
    "file_cargo": {
      "iconPath": "./icons/cargo_dark.svg"
    },
    "file_cargolock": {
      "iconPath": "./icons/cargoLock_dark.svg"
    },
    "file_cmake": {
      "iconPath": "./icons/CMake_dark.svg"
    },
    "file_pnpm": {
      "iconPath": "./icons/pnpm_dark.svg"
    },
    "file_tailwind": {
      "iconPath": "./icons/tailwind.svg"
    },
    "file_vite": {
      "iconPath": "./icons/vite_dark.svg"
    },
    "file_postcss": {
      "iconPath": "./icons/postcss.svg"
    },
    "file_angular": {
      "iconPath": "./icons/angularJS.svg"
    },
    "file_eslint": {
      "iconPath": "./icons/eslint.svg"
    },
    "file_cs": {
      "iconPath": "./icons/cs_dark.svg"
    },
    "file_cshtml": {
      "iconPath": "./icons/cshtml_dark.svg"
    },
    "file_csproj": {
      "iconPath": "./icons/csproj_dark.svg"
    },
    "file_ejs": {
      "iconPath": "./icons/ejs_dark.svg"
    },
    "file_dotenv": {
      "iconPath": "./icons/dotenv_dark.svg"
    },
    "file_log": {
      "iconPath": "./icons/log_dark.svg"
    },
    "file_cmd": {
      "iconPath": "./icons/cmd_dark.svg"
    },
    "file_ps1": {
      "iconPath": "./icons/powershell.png"
    },
    "file_nodejs": {
      "iconPath": "./icons/nodejs.svg"
    },
    "file_nodejs2": {
      "iconPath": "./icons/nodejs2.svg"
    },
    "file_sequelize": {
      "iconPath": "./icons/sequelize.svg"
    },
    "file_prisma": {
      "iconPath": "./icons/prisma.svg"
    },
    "folder_config": {
      "iconPath": "./icons/bench.svg"
    },
    "folder_config_open": {
      "iconPath": "./icons/bench-open.svg"
    },

    "_folder": { "iconPath": "./icons/folder/folder.svg" },
    "_folder_assets": { "iconPath": "./icons/folder/folder_assetsLight.svg" },
    "_folder_assets_open": {
      "iconPath": "./icons/folder/folder_assets_open.svg"
    },
    "_folder_bower": { "iconPath": "./icons/folder/folder_bower.svg" },
    "_folder_bower_open": {
      "iconPath": "./icons/folder/folder_bower_open.svg"
    },
    "_folder_ci": { "iconPath": "./icons/folder/folder_ciLight.svg" },
    "_folder_ci_open": { "iconPath": "./icons/folder/folder_ci_open.svg" },
    "_folder_css": { "iconPath": "./icons/folder/folder_cssLight.svg" },
    "_folder_css_open": { "iconPath": "./icons/folder/folder_css_open.svg" },
    "_folder_dark": { "iconPath": "./icons/folder/folder_darkLight.svg" },
    "_folder_dark_view": {
      "iconPath": "./icons/folder/folder_darkLight_view.svg"
    },
    "_folder_dark_validation": {
      "iconPath": "./icons/folder/folder_darkLight_validation.svg"
    },
    "_folder_dark_util": {
      "iconPath": "./icons/folder/folder_darkLight_util.svg"
    },
    "_folder_dark_route": {
      "iconPath": "./icons/folder/folder_darkLight_route.svg"
    },
    "_folder_dist": { "iconPath": "./icons/folder/folder_distLight.svg" },
    "_folder_dist_open": { "iconPath": "./icons/folder/folder_dist_open.svg" },
    "_folder_git": { "iconPath": "./icons/folder/folder_gitLight.svg" },
    "_folder_git_open": { "iconPath": "./icons/folder/folder_git_open.svg" },
    "_folder_github": { "iconPath": "./icons/folder/folder_githubLight.svg" },
    "_folder_github_open": {
      "iconPath": "./icons/folder/folder_github_open.svg"
    },
    "_folder_grpc": { "iconPath": "./icons/folder/folder_grpc.svg" },
    "_folder_grpc_open": { "iconPath": "./icons/folder/folder_grpc_open.svg" },
    "_folder_gulp": { "iconPath": "./icons/folder/folder_gulpLight.svg" },
    "_folder_gulp_open": { "iconPath": "./icons/folder/folder_gulp_open.svg" },
    "_folder_images": { "iconPath": "./icons/folder/folder_imagesLight.svg" },
    "_folder_images_open": {
      "iconPath": "./icons/folder/folder_images_open.svg"
    },
    "_folder_js": { "iconPath": "./icons/folder/folder_jsLight.svg" },
    "_folder_js_open": { "iconPath": "./icons/folder/folder_js_open.svg" },
    "_folder_light": { "iconPath": "./icons/folder/folder_lightLight.svg" },
    "_folder_nginx": { "iconPath": "./icons/folder/folder_nginxLight.svg" },
    "_folder_nginx_open": {
      "iconPath": "./icons/folder/folder_nginx_open.svg"
    },
    "_folder_node": { "iconPath": "./icons/folder/folder_nodeLight.svg" },
    "_folder_node_open": { "iconPath": "./icons/folder/folder_node_open.svg" },
    "_folder_open": { "iconPath": "./icons/folder/folder_open.svg" },
    "_folder_open_view": { "iconPath": "./icons/folder/folder_open_view.svg" },
    "_folder_open_validation": {
      "iconPath": "./icons/folder/folder_open_validation.svg"
    },
    "_folder_open_util": {
      "iconPath": "./icons/folder/folder_open_util.svg"
    },
    "_folder_open_route": {
      "iconPath": "./icons/folder/folder_open_route.svg"
    },
    "_folder_root_dark": {
      "iconPath": "./icons/folder/folder_root_darkLight.svg"
    },
    "_folder_root_light": {
      "iconPath": "./icons/folder/folder_root_lightLight.svg"
    },
    "_folder_root_open": { "iconPath": "./icons/folder/folder_root_open.svg" },
    "_folder_sass": { "iconPath": "./icons/folder/folder_sassLight.svg" },
    "_folder_sass_open": { "iconPath": "./icons/folder/folder_sass_open.svg" },
    "_folder_src": { "iconPath": "./icons/folder/folder_srcLight.svg" },
    "_folder_src_open": { "iconPath": "./icons/folder/folder_src_open.svg" },
    "_folder_test": { "iconPath": "./icons/folder/folder_testLight.svg" },
    "_folder_test_open": { "iconPath": "./icons/folder/folder_test_open.svg" },
    "_folder_vscode": { "iconPath": "./icons/folder/folder_vscodeLight.svg" },
    "_folder_vscode_open": {
      "iconPath": "./icons/folder/folder_vscode_open.svg"
    },

    "_file_actionscript": { "iconPath": "./icons/actionscript.svg" },
    "_file_ai": { "iconPath": "./icons/ai.svg" },
    "_file_android": { "iconPath": "./icons/android.svg" },
    "_file_angular-component": { "iconPath": "./icons/angular-component.svg" },
    "_file_angular-directive": { "iconPath": "./icons/angular-directive.svg" },
    "_file_angular-guard": { "iconPath": "./icons/angular-guard.svg" },
    "_file_angular-pipe": { "iconPath": "./icons/angular-pipe.svg" },
    "_file_angular-resolver": { "iconPath": "./icons/angular-resolver.svg" },
    "_file_angular-routing": { "iconPath": "./icons/angular-routing.svg" },
    "_file_angular-service": { "iconPath": "./icons/angular-service.svg" },
    "_file_angular": { "iconPath": "./icons/angular.svg" },
    "_file_applescript": { "iconPath": "./icons/applescript.svg" },
    "_file_arduino": { "iconPath": "./icons/arduino.svg" },
    "_file_assembly": { "iconPath": "./icons/assembly.svg" },
    "_file_astro": { "iconPath": "./icons/astro.svg" },
    "_file_audio": { "iconPath": "./icons/audio.svg" },
    "_file_autohotkey": { "iconPath": "./icons/autohotkey.svg" },
    "_file_babel": { "iconPath": "./icons/babel.svg" },
    "_file_blade": { "iconPath": "./icons/blade.svg" },
    "_file_bower": { "iconPath": "./icons/bower.svg" },
    "_file_browserlist": { "iconPath": "./icons/browserlist.svg" },
    "_file_c": { "iconPath": "./icons/c.svg" },
    "_file_cabal": { "iconPath": "./icons/cabal.svg" },
    "_file_cargo-lock": { "iconPath": "./icons/cargo-lock.svg" },
    "_file_certificate": { "iconPath": "./icons/certificate.svg" },
    "_file_changelog": { "iconPath": "./icons/changelog.svg" },
    "_file_clojure": { "iconPath": "./icons/clojure.svg" },
    "_file_cmake": { "iconPath": "./icons/cmake.svg" },
    "_file_cmd": { "iconPath": "./icons/cmd.svg" },
    "_file_coffee": { "iconPath": "./icons/coffee.svg" },
    "_file_coldfusion": { "iconPath": "./icons/coldfusion.svg" },
    "_file_conduct": { "iconPath": "./icons/conduct.svg" },
    "_file_console": { "iconPath": "./icons/console.svg" },
    "_file_contributing": { "iconPath": "./icons/contributing.svg" },
    "_file_cpp": { "iconPath": "./icons/cpp.svg" },
    "_file_credits": { "iconPath": "./icons/credits.svg" },
    "_file_crystal": { "iconPath": "./icons/crystal.svg" },
    "_file_csharp": { "iconPath": "./icons/csharp.svg" },
    "_file_css-map": { "iconPath": "./icons/css-map.svg" },
    "_file_css": { "iconPath": "./icons/css.svg" },
    "_file_dart": { "iconPath": "./icons/dart.svg" },
    "_file_database": { "iconPath": "./icons/database.svg" },
    "_file_dlang": { "iconPath": "./icons/dlang.svg" },
    "_file_docker": { "iconPath": "./icons/docker.svg" },
    "_file_document": { "iconPath": "./icons/document.svg" },
    "_file_dvc": { "iconPath": "./icons/dvc.svg" },
    "_file_elixir-lock": { "iconPath": "./icons/elixir-lock.svg" },
    "_file_elixir": { "iconPath": "./icons/elixir.svg" },
    "_file_elm": { "iconPath": "./icons/elm.svg" },
    "_file_email": { "iconPath": "./icons/email.svg" },
    "_file_erlang": { "iconPath": "./icons/erlang.svg" },
    "_file_eslint": { "iconPath": "./icons/eslint.svg" },
    "_file_ex": { "iconPath": "./icons/ex.svg" },
    "_file_exe": { "iconPath": "./icons/exe.svg" },
    "_file_favicon": { "iconPath": "./icons/favicon.svg" },
    "_file_dark": { "iconPath": "./icons/file_dark.svg" },
    "_file_lnk": { "iconPath": "./icons/file_lnk.svg" },
    "_file_mdx": { "iconPath": "./icons/mdx.svg" },
    "_file_firebase": { "iconPath": "./icons/firebase.svg" },
    "_file_flash": { "iconPath": "./icons/flash.svg" },
    "_file_flow": { "iconPath": "./icons/flow.svg" },
    "_file_font": { "iconPath": "./icons/font.svg" },
    "_file_fsharp": { "iconPath": "./icons/fsharp.svg" },
    "_file_gatsby": { "iconPath": "./icons/gatsby.svg" },
    "_file_git": { "iconPath": "./icons/git.svg" },
    "_file_github": { "iconPath": "./icons/github.svg" },
    "_file_gitlab": { "iconPath": "./icons/gitlab.svg" },
    "_file_go": { "iconPath": "./icons/go.svg" },
    "_file_gradle": { "iconPath": "./icons/gradle.svg" },
    "_file_graphql": { "iconPath": "./icons/graphql.svg" },
    "_file_graphviz": { "iconPath": "./icons/graphviz.svg" },
    "_file_groovy": { "iconPath": "./icons/groovy.svg" },
    "_file_grunt": { "iconPath": "./icons/grunt.svg" },
    "_file_gulp": { "iconPath": "./icons/gulp.svg" },
    "_file_haml": { "iconPath": "./icons/haml.svg" },
    "_file_handlebars": { "iconPath": "./icons/handlebars.svg" },
    "_file_haskell": { "iconPath": "./icons/haskell.svg" },
    "_file_haxe": { "iconPath": "./icons/haxe.svg" },
    "_file_html": { "iconPath": "./icons/html.svg" },
    "_file_image": { "iconPath": "./icons/image.svg" },
    "_file_ionic": { "iconPath": "./icons/ionic.svg" },
    "_file_java": { "iconPath": "./icons/java.svg" },
    "_file_jenkins": { "iconPath": "./icons/jenkins.svg" },
    "_file_jest": { "iconPath": "./icons/jest.svg" },
    "_file_js": { "iconPath": "./icons/js.svg" },
    "_file_js_map": { "iconPath": "./icons/js_map.svg" },
    "_file_json": { "iconPath": "./icons/json.svg" },
    "_file_julia": { "iconPath": "./icons/julia.svg" },
    "_file_jupyter": { "iconPath": "./icons/jupyter.svg" },
    "_file_key": { "iconPath": "./icons/key.svg" },
    "_file_kotlin": { "iconPath": "./icons/kotlin.svg" },
    "_file_less": { "iconPath": "./icons/less.svg" },
    "_file_lib": { "iconPath": "./icons/lib.svg" },
    "_file_license": { "iconPath": "./icons/license.svg" },
    "_file_liquid": { "iconPath": "./icons/liquid.svg" },
    "_file_lua": { "iconPath": "./icons/lua.svg" },
    "_file_markdown": { "iconPath": "./icons/markdown.svg" },
    "_file_markojs": { "iconPath": "./icons/markojs.svg" },
    "_file_markup": { "iconPath": "./icons/markup.svg" },
    "_file_matlab": { "iconPath": "./icons/matlab.svg" },
    "_file_mjml": { "iconPath": "./icons/mjml.svg" },
    "_file_movie": { "iconPath": "./icons/movie.svg" },
    "_file_mustache": { "iconPath": "./icons/mustache.svg" },
    "_file_mxml": { "iconPath": "./icons/mxml.svg" },
    "_file_nextjs": { "iconPath": "./icons/nextjs.svg" },
    "_file_nginx": { "iconPath": "./icons/nginx.svg" },
    "_file_nix": { "iconPath": "./icons/nix.svg" },
    "_file_node": { "iconPath": "./icons/node.svg" },
    "_file_note": { "iconPath": "./icons/note.svg" },
    "_file_now": { "iconPath": "./icons/now.svg" },
    "_file_npm": { "iconPath": "./icons/npm.svg" },
    "_file_nunjucks": { "iconPath": "./icons/nunjucks.svg" },
    "_file_nuxtconfig": { "iconPath": "./icons/nuxtconfig.svg" },
    "_file_ocaml": { "iconPath": "./icons/ocaml.svg" },
    "_file_odin": { "iconPath": "./icons/odin.svg" },
    "_file_package-lock": { "iconPath": "./icons/package-lock.svg" },
    "_file_pdf": { "iconPath": "./icons/pdf.svg" },
    "_file_perl": { "iconPath": "./icons/perl.svg" },
    "_file_php": { "iconPath": "./icons/php.svg" },
    "_file_pipfile-lock": { "iconPath": "./icons/pipfile-lock.svg" },
    "_file_pipfile": { "iconPath": "./icons/pipfile.svg" },
    "_file_polymer": { "iconPath": "./icons/polymer.svg" },
    "_file_postcss": { "iconPath": "./icons/postcss.svg" },
    "_file_powerpoint": { "iconPath": "./icons/powerpoint.svg" },
    "_file_prettier": { "iconPath": "./icons/prettier.svg" },
    "_file_prisma": { "iconPath": "./icons/prisma.svg" },
    "_file_procfile": { "iconPath": "./icons/procfile.svg" },
    "_file_protobuf": { "iconPath": "./icons/protobuf.svg" },
    "_file_psd": { "iconPath": "./icons/psd.svg" },
    "_file_pug": { "iconPath": "./icons/pug.svg" },
    "_file_puppet": { "iconPath": "./icons/puppet.svg" },
    "_file_python": { "iconPath": "./icons/python.svg" },
    "_file_r": { "iconPath": "./icons/r.svg" },
    "_file_rails": { "iconPath": "./icons/rails.svg" },
    "_file_raml": { "iconPath": "./icons/raml.svg" },
    "_file_react": { "iconPath": "./icons/react.svg" },
    "_file_readme": { "iconPath": "./icons/readme.svg" },
    "_file_reason": { "iconPath": "./icons/reason.svg" },
    "_file_rest": { "iconPath": "./icons/rest.svg" },
    "_file_rollup": { "iconPath": "./icons/rollup.svg" },
    "_file_ruby": { "iconPath": "./icons/ruby.svg" },
    "_file_rust": { "iconPath": "./icons/rust.svg" },
    "_file_salesforce": { "iconPath": "./icons/salesforce.svg" },
    "_file_sass": { "iconPath": "./icons/sass.svg" },
    "_file_scala": { "iconPath": "./icons/scala.svg" },
    "_file_settings": { "iconPath": "./icons/settings.svg" },
    "_file_sketch": { "iconPath": "./icons/sketch.svg" },
    "_file_slim": { "iconPath": "./icons/slim.svg" },
    "_file_smallbasic": { "iconPath": "./icons/smallbasic.svg" },
    "_file_source": { "iconPath": "./icons/source.svg" },
    "_file_sql-lite": { "iconPath": "./icons/sql-lite.svg" },
    "_file_sql": { "iconPath": "./icons/sql.svg" },
    "_file_storybook": { "iconPath": "./icons/storybook.svg" },
    "_file_stylelint": { "iconPath": "./icons/stylelint.svg" },
    "_file_stylus": { "iconPath": "./icons/stylus.svg" },
    "_file_sublime": { "iconPath": "./icons/sublime.svg" },
    "_file_svelte": { "iconPath": "./icons/svelte.svg" },
    "_file_svg": { "iconPath": "./icons/svg.svg" },
    "_file_swc": { "iconPath": "./icons/swc.svg" },
    "_file_swift": { "iconPath": "./icons/swift.svg" },
    "_file_swig": { "iconPath": "./icons/swig.svg" },
    "_file_table": { "iconPath": "./icons/table.svg" },
    "_file_tailwind": { "iconPath": "./icons/tailwind.svg" },
    "_file_tcl": { "iconPath": "./icons/tcl.svg" },
    "_file_terraform": { "iconPath": "./icons/terraform.svg" },
    "_file_test": { "iconPath": "./icons/test.svg" },
    "_file_tex": { "iconPath": "./icons/tex.svg" },
    "_file_todo": { "iconPath": "./icons/todo.svg" },
    "_file_tune": { "iconPath": "./icons/tune.svg" },
    "_file_twig": { "iconPath": "./icons/twig.svg" },
    "_file_typescript": { "iconPath": "./icons/typescript.svg" },
    "_file_typescript_def": { "iconPath": "./icons/typescript_def.svg" },
    "_file_unknown": { "iconPath": "./icons/unknown.svg" },
    "_file_url": { "iconPath": "./icons/url.svg" },
    "_file_vhdl": { "iconPath": "./icons/vhdl.svg" },
    "_file_virtual": { "iconPath": "./icons/virtual.svg" },
    "_file_visualstudio": { "iconPath": "./icons/visualstudio.svg" },
    "_file_vite": { "iconPath": "./icons/vite.svg" },
    "_file_vlang": { "iconPath": "./icons/vlang.svg" },
    "_file_vue": { "iconPath": "./icons/vue.svg" },
    "_file_wakatime": { "iconPath": "./icons/wakatime.svg" },
    "_file_webpack": { "iconPath": "./icons/webpack.svg" },
    "webpack": { "iconPath": "./icons/webpack.svg" },
    "_file_word": { "iconPath": "./icons/word.svg" },
    "_file_wrangler": { "iconPath": "./icons/wrangler.svg" },
    "_file_xaml": { "iconPath": "./icons/xaml.svg" },
    "_file_xml": { "iconPath": "./icons/xml.svg" },
    "_file_yaml": { "iconPath": "./icons/yaml.svg" },
    "_file_yarn-lock": { "iconPath": "./icons/yarn-lock.svg" },
    "_file_yarn": { "iconPath": "./icons/yarn.svg" },
    "_file_zephyr": { "iconPath": "./icons/zephyr.svg" },
    "_file_zig": { "iconPath": "./icons/zig.svg" },
    "_file_zip": { "iconPath": "./icons/zip.svg" }
  },
  "file": "file_any",
  "folder": "_folder_dark",
  "folderExpanded": "_folder_open",
  "rootFolder": "_folder_root_dark",
  "rootFolderExpanded": "_folder_root_open",
  "folderNames": {},
  "folderNamesExpanded": {},
  "fileNames": {
    "contributing.md": "_file_contributing",
    "contributing.rst": "_file_contributing",
    "contributing.txt": "_file_contributing",
    "contributing": "_file_contributing",
    "changelog": "_file_changelog",
    "changelog.md": "_file_changelog",
    "changelog.rst": "_file_changelog",
    "changelog.txt": "_file_changelog",
    "changes": "_file_changelog",
    "changes.md": "_file_changelog",
    "changes.rst": "_file_changelog",
    "changes.txt": "_file_changelog",
    "code_of_conduct.md": "_file_conduct",
    "code_of_conduct.txt": "_file_conduct",
    "code_of_conduct": "_file_conduct",
    "readme.md": "_file_readme",
    "readme.rst": "_file_readme",
    "readme.txt": "_file_readme",
    "readme": "_file_readme",
    "roadmap.md": "roadmap",
    "roadmap.txt": "roadmap",
    "timeline.md": "roadmap",
    "timeline.txt": "roadmap",
    "milestones.md": "roadmap",
    "milestones.txt": "roadmap",
    "security.md": "lock",
    "security.txt": "lock",
    "security": "lock",
    ".renovaterc": "renovate",
    ".renovaterc.json": "renovate",
    "renovate-config.json": "renovate",
    "renovate.json": "renovate",
    "renovate.json5": "renovate",
    "capacitor.config.json": "capacitor",
    "capacitor.config.ts": "capacitor",
    "karma.conf.js": "karma",
    "karma.conf.ts": "karma",
    "karma.conf.coffee": "karma",
    "karma.config.js": "karma",
    "karma.config.ts": "karma",
    "karma-main.js": "karma",
    "karma-main.ts": "karma",
    "ionic.config.json": "_file_ionic",
    ".io-config.json": "_file_ionic",
    "vercel.json": "vercel",
    ".vercelignore": "vercel",
    "now.json": "vercel",
    ".nowignore": "vercel",
    "gulpfile.js": "_file_gulp",
    "gulpfile.mjs": "_file_gulp",
    "gulpfile.ts": "_file_gulp",
    "gulpfile.cts": "_file_gulp",
    "gulpfile.mts": "_file_gulp",
    "gulpfile.babel.js": "_file_gulp",
    ".babelrc": "_file_babel",
    ".babelrc.cjs": "_file_babel",
    ".babelrc.js": "_file_babel",
    ".babelrc.mjs": "_file_babel",
    ".babelrc.json": "_file_babel",
    "babel.config.cjs": "_file_babel",
    "babel.config.js": "_file_babel",
    "babel.config.mjs": "_file_babel",
    "babel.config.json": "_file_babel",
    "babel-transform.js": "_file_babel",
    ".babel-plugin-macrosrc": "_file_babel",
    ".babel-plugin-macrosrc.json": "_file_babel",
    ".babel-plugin-macrosrc.yaml": "_file_babel",
    ".babel-plugin-macrosrc.yml": "_file_babel",
    ".babel-plugin-macrosrc.js": "_file_babel",
    "babel-plugin-macros.config.js": "_file_babel",
    "jsconfig.json": "jsconfig",
    "next.config.js": "_file_nextjs",
    "next.config.mjs": "_file_nextjs",
    "next.config.ts": "_file_nextjs",
    "next.config.mts": "_file_nextjs",
    "browserslist": "_file_browserlist",
    ".browserslistrc": "_file_browserlist",
    ".stylelintrc": "_file_stylelint",
    "stylelint.config.js": "_file_stylelint",
    "stylelint.config.cjs": "_file_stylelint",
    "stylelint.config.mjs": "_file_stylelint",
    ".stylelintrc.json": "_file_stylelint",
    ".stylelintrc.yaml": "_file_stylelint",
    ".stylelintrc.yml": "_file_stylelint",
    ".stylelintrc.js": "_file_stylelint",
    ".stylelintrc.cjs": "_file_stylelint",
    ".stylelintignore": "_file_stylelint",
    ".stylelintcache": "_file_stylelint",
    ".htaccess": "file_xml",
    "gradle.properties": "_file_gradle",
    "gradlew": "_file_gradle",
    "gradle-wrapper.properties": "_file_gradle",
    "svgo.config.js": "svgo",
    "svgo.config.cjs": "svgo",
    "svgo.config.mjs": "svgo",
    "webpack.js": "webpack",
    "webpack.cjs": "webpack",
    "webpack.mjs": "webpack",
    "webpack.ts": "webpack",
    "webpack.cts": "webpack",
    "webpack.mts": "webpack",
    "webpack.base.js": "webpack",
    "webpack.base.cjs": "webpack",
    "webpack.base.mjs": "webpack",
    "webpack.base.ts": "webpack",
    "webpack.base.cts": "webpack",
    "webpack.base.mts": "webpack",
    "webpack.config.js": "webpack",
    "webpack.config.cjs": "webpack",
    "webpack.config.mjs": "webpack",
    "webpack.config.ts": "webpack",
    "webpack.config.cts": "webpack",
    "webpack.config.mts": "webpack",
    "webpack.common.js": "webpack",
    "webpack.common.cjs": "webpack",
    "webpack.common.mjs": "webpack",
    "webpack.common.ts": "webpack",
    "webpack.common.cts": "webpack",
    "webpack.common.mts": "webpack",
    "webpack.config.common.js": "webpack",
    "webpack.config.common.cjs": "webpack",
    "webpack.config.common.mjs": "webpack",
    "webpack.config.common.ts": "webpack",
    "webpack.config.common.cts": "webpack",
    "webpack.config.common.mts": "webpack",
    "webpack.config.common.babel.js": "webpack",
    "webpack.config.common.babel.ts": "webpack",
    "webpack.dev.js": "webpack",
    "webpack.dev.cjs": "webpack",
    "webpack.dev.mjs": "webpack",
    "webpack.dev.ts": "webpack",
    "webpack.dev.cts": "webpack",
    "webpack.dev.mts": "webpack",
    "webpack.development.js": "webpack",
    "webpack.development.cjs": "webpack",
    "webpack.development.mjs": "webpack",
    "webpack.development.ts": "webpack",
    "webpack.development.cts": "webpack",
    "webpack.development.mts": "webpack",
    "webpack.config.dev.js": "webpack",
    "webpack.config.dev.cjs": "webpack",
    "webpack.config.dev.mjs": "webpack",
    "webpack.config.dev.ts": "webpack",
    "webpack.config.dev.cts": "webpack",
    "webpack.config.dev.mts": "webpack",
    "webpack.config.dev.babel.js": "webpack",
    "webpack.config.dev.babel.ts": "webpack",
    "webpack.config.main.js": "webpack",
    "webpack.config.renderer.ts": "webpack",
    "webpack.mix.js": "webpack",
    "webpack.mix.cjs": "webpack",
    "webpack.mix.mjs": "webpack",
    "webpack.mix.ts": "webpack",
    "webpack.mix.cts": "webpack",
    "webpack.mix.mts": "webpack",
    "webpack.prod.js": "webpack",
    "webpack.prod.cjs": "webpack",
    "webpack.prod.mjs": "webpack",
    "webpack.prod.ts": "webpack",
    "webpack.prod.cts": "webpack",
    "webpack.prod.mts": "webpack",
    "webpack.prod.config.js": "webpack",
    "webpack.prod.config.cjs": "webpack",
    "webpack.prod.config.mjs": "webpack",
    "webpack.prod.config.ts": "webpack",
    "webpack.prod.config.cts": "webpack",
    "webpack.prod.config.mts": "webpack",
    "webpack.production.js": "webpack",
    "webpack.production.cjs": "webpack",
    "webpack.production.mjs": "webpack",
    "webpack.production.ts": "webpack",
    "webpack.production.cts": "webpack",
    "webpack.production.mts": "webpack",
    "webpack.server.js": "webpack",
    "webpack.server.cjs": "webpack",
    "webpack.server.mjs": "webpack",
    "webpack.server.ts": "webpack",
    "webpack.server.cts": "webpack",
    "webpack.server.mts": "webpack",
    "webpack.client.js": "webpack",
    "webpack.client.cjs": "webpack",
    "webpack.client.mjs": "webpack",
    "webpack.client.ts": "webpack",
    "webpack.client.cts": "webpack",
    "webpack.client.mts": "webpack",
    "webpack.config.server.js": "webpack",
    "webpack.config.server.cjs": "webpack",
    "webpack.config.server.mjs": "webpack",
    "webpack.config.server.ts": "webpack",
    "webpack.config.server.cts": "webpack",
    "webpack.config.server.mts": "webpack",
    "webpack.config.client.js": "webpack",
    "webpack.config.client.cjs": "webpack",
    "webpack.config.client.mjs": "webpack",
    "webpack.config.client.ts": "webpack",
    "webpack.config.client.cts": "webpack",
    "webpack.config.client.mts": "webpack",
    "webpack.config.production.babel.js": "webpack",
    "webpack.config.production.babel.ts": "webpack",
    "webpack.config.prod.babel.js": "webpack",
    "webpack.config.prod.babel.cjs": "webpack",
    "webpack.config.prod.babel.mjs": "webpack",
    "webpack.config.prod.babel.ts": "webpack",
    "webpack.config.prod.babel.cts": "webpack",
    "webpack.config.prod.babel.mts": "webpack",
    "webpack.config.prod.js": "webpack",
    "webpack.config.prod.cjs": "webpack",
    "webpack.config.prod.mjs": "webpack",
    "webpack.config.prod.ts": "webpack",
    "webpack.config.prod.cts": "webpack",
    "webpack.config.prod.mts": "webpack",
    "webpack.config.production.js": "webpack",
    "webpack.config.production.cjs": "webpack",
    "webpack.config.production.mjs": "webpack",
    "webpack.config.production.ts": "webpack",
    "webpack.config.production.cts": "webpack",
    "webpack.config.production.mts": "webpack",
    "webpack.config.staging.js": "webpack",
    "webpack.config.staging.cjs": "webpack",
    "webpack.config.staging.mjs": "webpack",
    "webpack.config.staging.ts": "webpack",
    "webpack.config.staging.cts": "webpack",
    "webpack.config.staging.mts": "webpack",
    "webpack.config.babel.js": "webpack",
    "webpack.config.babel.ts": "webpack",
    "webpack.config.base.babel.js": "webpack",
    "webpack.config.base.babel.ts": "webpack",
    "webpack.config.base.js": "webpack",
    "webpack.config.base.cjs": "webpack",
    "webpack.config.base.mjs": "webpack",
    "webpack.config.base.ts": "webpack",
    "webpack.config.base.cts": "webpack",
    "webpack.config.base.mts": "webpack",
    "webpack.config.staging.babel.js": "webpack",
    "webpack.config.staging.babel.ts": "webpack",
    "webpack.config.coffee": "webpack",
    "webpack.config.test.js": "webpack",
    "webpack.config.test.cjs": "webpack",
    "webpack.config.test.mjs": "webpack",
    "webpack.config.test.ts": "webpack",
    "webpack.config.test.cts": "webpack",
    "webpack.config.test.mts": "webpack",
    "webpack.config.vendor.js": "webpack",
    "webpack.config.vendor.cjs": "webpack",
    "webpack.config.vendor.mjs": "webpack",
    "webpack.config.vendor.ts": "webpack",
    "webpack.config.vendor.cts": "webpack",
    "webpack.config.vendor.mts": "webpack",
    "webpack.config.vendor.production.js": "webpack",
    "webpack.config.vendor.production.cjs": "webpack",
    "webpack.config.vendor.production.mjs": "webpack",
    "webpack.config.vendor.production.ts": "webpack",
    "webpack.config.vendor.production.cts": "webpack",
    "webpack.config.vendor.production.mts": "webpack",
    "webpack.test.js": "webpack",
    "webpack.test.cjs": "webpack",
    "webpack.test.mjs": "webpack",
    "webpack.test.ts": "webpack",
    "webpack.test.cts": "webpack",
    "webpack.test.mts": "webpack",
    "webpack.dist.js": "webpack",
    "webpack.dist.cjs": "webpack",
    "webpack.dist.mjs": "webpack",
    "webpack.dist.ts": "webpack",
    "webpack.dist.cts": "webpack",
    "webpack.dist.mts": "webpack",
    "webpackfile.js": "webpack",
    "webpackfile.cjs": "webpack",
    "webpackfile.mjs": "webpack",
    "webpackfile.ts": "webpack",
    "webpackfile.cts": "webpack",
    "webpackfile.mts": "webpack",
    "cname": "globe",
    "nodemon.json": "nodemon",
    "tsconfig.json": "tsconfig",
    "tsconfig.app.json": "tsconfig",
    "tsconfig.editor.json": "tsconfig",
    "tsconfig.spec.json": "tsconfig",
    "tsconfig.base.json": "tsconfig",
    "tsconfig.build.json": "tsconfig",
    "tsconfig.eslint.json": "tsconfig",
    "tsconfig.lib.json": "tsconfig",
    "tsconfig.lib.prod.json": "tsconfig",
    "tsconfig.node.json": "tsconfig",
    "tsconfig.test.json": "tsconfig",
    "tsconfig.e2e.json": "tsconfig",
    "tsconfig.web.json": "tsconfig",
    "tsconfig.webworker.json": "tsconfig",
    "tsconfig.worker.json": "tsconfig",
    "tsconfig.config.json": "tsconfig",
    "tsconfig.vitest.json": "tsconfig",
    "tsconfig.cjs.json": "tsconfig",
    "tsconfig.esm.json": "tsconfig",
    "tsconfig.mjs.json": "tsconfig",
    "tsconfig.doc.json": "tsconfig",
    "tsconfig.paths.json": "tsconfig",
    "tsconfig.main.json": "tsconfig",
    "tsconfig.renderer.json": "tsconfig",
    "jest.config.js": "_file_jest",
    "jest.config.ts": "_file_jest",
    "jest.config.json": "_file_jest",
    "jest.setup.js": "_file_jest",
    "jest.setup.ts": "_file_jest",
    "jest.json": "_file_jest",
    ".jestrc": "_file_jest",
    "jest.teardown.js": "_file_jest",
    "pre-commit": "_file_console",
    ".prettierrc": "_file_prettier",
    ".prettierrc.cjs": "_file_prettier",
    ".prettierrc.js": "_file_prettier",
    ".prettierrc.json": "_file_prettier",
    ".prettierrc.json5": "_file_prettier",
    ".prettierrc.toml": "_file_prettier",
    ".prettierrc.yaml": "_file_prettier",
    ".prettierrc.yml": "_file_prettier",
    "prettier.config.cjs": "_file_prettier",
    "prettier.config.js": "_file_prettier",
    ".prettierignore": "_file_prettier",
    ".prettierignore-sync": "_file_prettier",
    "copying": "certificate",
    "copying.md": "certificate",
    "copying.rst": "certificate",
    "copying.txt": "certificate",
    "copyright": "certificate",
    "copyright.md": "certificate",
    "copyright.rst": "certificate",
    "copyright.txt": "certificate",
    "license": "certificate",
    "license-agpl": "certificate",
    "license-apache": "certificate",
    "license-bsd": "certificate",
    "license-mit": "certificate",
    "license-gpl": "certificate",
    "license-lgpl": "certificate",
    "license.md": "certificate",
    "license.rst": "certificate",
    "license.txt": "certificate",
    "licence": "certificate",
    "licence-agpl": "certificate",
    "licence-apache": "certificate",
    "licence-bsd": "certificate",
    "licence-mit": "certificate",
    "licence-gpl": "certificate",
    "licence-lgpl": "certificate",
    "licence.md": "certificate",
    "licence.rst": "certificate",
    "licence.txt": "certificate",
    ".gitignore": "file_gitignore",
    ".gitattributes": "file_gitignore",
    ".gitmodules": "file_gitignore",
    ".editorconfig": "file_editorconfig",
    ".yarnrc": "file_yarn",
    "yarn-error.log": "file_yarn",
    "yarn.lock": "_file_yarn-lock",
    "README": "file_markdown",
    ".dockerignore": "file_ignored",
    "Dockerfile": "file_docker",
    "Dockerfile.test": "file_docker",
    "Dockerfile.staging": "file_docker",
    "Dockerfile.production": "file_docker",
    "Gemfile": "file_gemfile",
    "Gemfile.lock": "file_gemfile",
    "Makefile": "file_makefile",
    ".env": "file_dotenv",
    ".env.local": "file_any",
    ".env.test": "file_any",
    ".env.example": "file_any",
    ".env.development": "file_any",
    ".env.production": "file_any",
    ".env.test.local": "file_any",
    ".env.development.local": "file_any",
    ".env.production.local": "file_any",
    "Cargo.toml": "file_cargo",
    "rust-toolchain.toml": "file_cargo",
    "Cargo.lock": "file_cargolock",
    "CMakeLists.txt": "file_cmake",
    "pnpm-lock.yaml": "file_pnpm",
    "pnpm-workspace.yaml": "file_pnpm",
    "tailwind.config.js": "file_tailwind",
    "tailwind.config.cjs": "file_tailwind",
    "tailwind.config.ts": "file_tailwind",
    "vite.config.js": "file_vite",
    "vite.config.cjs": "file_vite",
    "vite.config.ts": "file_vite",
    "postcss.config.js": "file_postcss",
    "postcss.config.cjs": "file_postcss",
    "postcss.config.ts": "file_postcss",
    "angular.json": "file_angular",
    ".eslintrc": "file_eslint",
    ".eslintrc.cjs": "file_eslint",
    ".eslintrc.js": "file_eslint",
    ".eslintrc.ts": "file_eslint",
    ".eslintrc.json": "file_eslint",
    ".eslintrc.yml": "file_eslint",
    ".eslintrc.yaml": "file_eslint",
    ".eslintignore": "file_eslint",
    "package.json": "_file_npm",
    "package-lock.json": "_file_package-lock",
    ".sequelizerc": "file_sequelize"
  },
  "languageIds": {
    "tex": "_file_tex",
    "doctex": "_file_tex",
    "latex": "_file_tex",
    "latex-expl3": "_file_tex",
    "ejs": "file_ejs",
    "hlsl": "shader",
    "glsl": "shader",
    "wgsl": "shader",
    "bat": "_file_cmd",
    "c": "_file_c",
    "clojure": "_file_clojure",
    "coffeescript": "_file_coffee",
    "cpp": "_file_cpp",
    "cuda-cpp": "_file_cpp",
    "csharp": "_file_csharp",
    "css": "_file_css",
    "dart": "_file_dart",
    "diff": "_file_git",
    "dockerfile": "_file_docker",
    "dockercompose": "_file_docker",
    "fsharp": "_file_fsharp",
    "git-commit": "_file_git",
    "git-rebase": "_file_git",
    "git": "_file_git",
    "go": "_file_go",
    "groovy": "_file_groovy",
    "handlebars": "_file_handlebars",
    "haxe": "_file_haxe",
    "html": "file_html",
    "hxml": "_file_haxe",
    "ignore": "_file_git",
    "ini": "_file_settings",
    "jade": "_file_pug",
    "java": "_file_java",
    "javascript": "_file_js",
    "javascriptreact": "_file_react",
    "json": "_file_json",
    "jsonl": "_file_json",
    "jsonc": "_file_json",
    "less": "_file_less",
    "lua": "_file_lua",
    "makefile": "_file_settings",
    "markdown": "_file_markdown",
    "marko": "_file_markojs",
    "matlab": "_file_matlab",
    "ng-template": "_file_angular",
    "nunjucks": "_file_nunjucks",
    "objective-c": "_file_matlab",
    "objective-cpp": "_file_cpp",
    "perl": "_file_perl",
    "prisma": "_file_prisma",
    "perl6": "_file_perl",
    "php": "_file_php",
    "plaintext": "_file_document",
    "polymer": "_file_polymer",
    "powershell": "_file_console",
    "properties": "_file_settings",
    "proto3": "_file_protobuf",
    "python": "_file_python",
    "r": "_file_r",
    "ruby": "_file_ruby",
    "rust": "_file_rust",
    "scss": "_file_sass",
    "shellscript": "_file_console",
    "sql": "_file_database",
    "swift": "_file_swift",
    "typescript": "_file_typescript",
    "typescriptreact": "_file_react",
    "v": "_file_vlang",
    "vb": "_file_visualstudio",
    "xml": "_file_xml",
    "xsl": "_file_xml",
    "yaml": "_file_yaml",
    "dotenv": "_file_tune",
    "crystal": "_file_crystal",
    "ecr": "_file_crystal",
    "slang": "_file_crystal",
    "apex": "_file_salesforce",
    "apex-anon": "_file_salesforce",
    "vhdl": "_file_vhdl",
    "nix": "_file_nix",
    "zig": "_file_zig",
    "lang-cfml": "coldfusion",
    "cfml": "coldfusion",
    "bibtex": "lib",
    "bibtex-style": "lib",
    "vue": "_file_vue",
    "graphql": "_file_graphql",
    "julia": "_file_julia",
    "juliamarkdown": "_file_julia"
  },
  "fileExtensions": {
    "jsconfig.json": "jsconfig",
    "ad": "asciidoc",
    "adoc": "asciidoc",
    "asciidoc": "asciidoc",
    "surrealql": "_file_surrealql",
    "surql": "_file_surrealql",
    "astro": "_file_astro",
    "7zip": "_file_zip",
    "a51": "_file_assembly",
    "accdb": "_file_database",
    "aea": "_file_assembly",
    "agc": "_file_assembly",
    "ags": "_file_assembly",
    "ahk": "_file_autohotkey",
    "ai": "_file_ai",
    "aiff": "_file_audio",
    "ami": "_file_image",
    "applescript": "_file_applescript",
    "apx": "_file_image",
    "argus": "_file_assembly",
    "asc": "_file_key",
    "ascx": "_file_html",
    "asm": "_file_assembly",
    "asp": "_file_html",
    "aspx": "_file_html",
    "avi": "_file_movie",
    "awk": "_file_console",
    "bat": "_file_cmd",
    "binsource": "_file_assembly",
    "bmap": "_file_font",
    "bmp": "_file_image",
    "bpg": "_file_image",
    "brk": "_file_image",
    "bzip2": "_file_zip",
    "c++": "_file_cpp",
    "cabal": "_file_cabal",
    "clj": "_file_clojure",
    "cls": "_file_salesforce",
    "cmake": "_file_cmake",
    "cmx": "_file_ocaml",
    "coffee": "_file_coffee",
    "component.js": "_file_angular-component",
    "component.ts": "_file_angular-component",
    "config": "_file_settings",
    "csh": "_file_console",
    "css.map": "_file_cssmap",
    "csx": "_file_csharp",
    "cur": "_file_image",
    "d.ts": "_file_typescript_def",
    "db": "_file_database",
    "dds": "_file_image",
    "directive.js": "_file_angular-directive",
    "directive.ts": "_file_angular-directive",
    "dlc": "_file_settings",
    "dll": "_file_settings",
    "dng": "_file_image",
    "do": "_file_todo",
    "doc": "_file_word",
    "dockerfile": "_file_docker",
    "dockerignore": "_file_docker",
    "docx": "_file_word",
    "dtd": "_file_xml",
    "dvc": "_file_dvc",
    "eex": "_file_ex",
    "elm": "_file_elm",
    "eps": "_file_svg",
    "erl": "_file_erlang",
    "esx": "_file_js",
    "ex": "_file_ex",
    "exe": "_file_exe",
    "exr": "_file_image",
    "exs": "_file_ex",
    "filter.js": "_file_angular-pipe",
    "fish": "_file_console",
    "flac": "_file_audio",
    "flv": "_file_movie",
    "fnt": "_file_font",
    "font": "_file_font",
    "fonts": "_file_font",
    "fpx": "_file_image",
    "fs": "_file_fsharp",
    "fsi": "_file_fsharp",
    "fsproj": "_file_fsharp",
    "fsx": "_file_fsharp",
    "gbr": "_file_image",
    "gifv": "_file_movie",
    "gradle": "_file_gradle",
    "graphqlconfig": "_file_graphql",
    "groovy": "_file_groovy",
    "guard.js": "_file_angular-guard",
    "guard.ts": "_file_angular-guard",
    "gv": "_file_graphviz",
    "gzip": "_file_zip",
    "haml": "_file_haml",
    "hbs": "_file_handlebars",
    "hs": "_file_haskell",
    "hx": "_file_haxe",
    "ics": "_file_email",
    "img": "_file_image",
    "iml": "_file_xml",
    "inc": "_file_assembly",
    "ini": "_file_settings",
    "inky.php": "_file_blade",
    "ino": "_file_arduino",
    "ipynb": "_file_jupyter",
    "jade": "_file_pug",
    "jar": "_file_java",
    "jb2": "_file_image",
    "jbig2": "_file_image",
    "jng": "_file_image",
    "js.map": "_file_jsmap",
    "jsonc": "_file_json",
    "jsp": "_file_java",
    "jxr": "_file_image",
    "key": "_file_key",
    "ksh": "_file_console",
    "liquid": "_file_liquid",
    "lit": "_file_html",
    "lnk": "_file_lnk",
    "lock": "lock",
    "lua": "_file_lua",
    "m": "_file_matlab",
    "m2v": "_file_movie",
    "m4a": "_file_audio",
    "m4v": "_file_movie",
    "manifest": "_file_xml",
    "markdown.rendered": "_file_markdown",
    "markdown": "_file_markdown",
    "marko": "_file_markojs",
    "matlab": "_file_matlab",
    "md.rendered": "_file_markdown",
    "mdb": "_file_database",
    "mdx": "_file_mdx",
    "mitigus": "_file_assembly",
    "mjml": "_file_mjml",
    "mjs.map": "_file_js_map",
    "mkv": "_file_movie",
    "ml": "_file_ocaml",
    "mli": "_file_ocaml",
    "mm": "_file_cpp",
    "module.js": "_file_angular",
    "module.ts": "_file_angular",
    "mov": "_file_movie",
    "mp2": "_file_movie",
    "mp3": "_file_audio",
    "mp4": "_file_movie",
    "mpe": "_file_movie",
    "mpeg": "_file_movie",
    "mpg": "_file_movie",
    "mpv": "_file_movie",
    "mrf": "_file_font",
    "ms": "_file_assembly",
    "msi": "_file_exe",
    "mustache": "_file_mustache",
    "mxml": "_file_mxml",
    "nasm": "_file_assembly",
    "ng-template": "_file_angular",
    "njk": "_file_nunjucks",
    "note": "_file_note",
    "ntf": "_file_font",
    "odttf": "_file_font",
    "ogg": "_file_movie",
    "ogv": "_file_movie",
    "otf": "_file_font",
    "patch": "_file_git",
    "pbm": "_file_image",
    "pcss": "_file_postcss",
    "postcss": "_file_postcss",
    "pdb": "_file_database",
    "pdf": "_file_pdf",
    "pem": "_file_key",
    "pgf": "_file_image",
    "pic": "_file_image",
    "pipe.js": "_file_angular-pipe",
    "pipe.ts": "_file_angular-pipe",
    "pl": "_file_perl",
    "plist": "_file_xml",
    "pm": "_file_perl",
    "pot": "_file_powerpoint",
    "potm": "_file_powerpoint",
    "potx": "_file_powerpoint",
    "pp": "_file_puppet",
    "ppa": "_file_powerpoint",
    "ppam": "_file_powerpoint",
    "pps": "_file_powerpoint",
    "ppsm": "_file_powerpoint",
    "ppsx": "_file_powerpoint",
    "ppt": "_file_powerpoint",
    "pptm": "_file_powerpoint",
    "pptx": "_file_powerpoint",
    "prefs": "_file_settings",
    "project": "_file_xml",
    "prop": "_file_settings",
    "props": "_file_settings",
    "proto": "_file_protobuf",
    "psb": "_file_psd",
    "psd": "_file_psd",
    "pub": "_file_key",
    "pug": "_file_pug",
    "pzip": "_file_zip",
    "qt": "_file_movie",
    "r": "_file_r",
    "rails": "_file_rails",
    "raml": "_file_raml",
    "raw": "_file_image",
    "re": "_file_reason",
    "rei": "_file_reason",
    "resolver.js": "_file_angular-resolver",
    "resolver.ts": "_file_angular-resolver",
    "resx": "_file_xml",
    "rm": "_file_movie",
    "rmvb": "_file_movie",
    "routing.js": "_file_angular-routing",
    "routing.ts": "_file_angular-routing",
    "rst": "_file_markdown",
    "rtf": "_file_word",
    "s": "_file_assembly",
    "sb": "_file_smallbasic",
    "settings": "_file_settings",
    "sketch": "_file_sketch",
    "sln": "_file_visualstudio",
    "smallbasic": "_file_smallbasic",
    "sqlite": "_file_database",
    "stories.js": "_file_storybook",
    "stories.jsx": "_file_storybook",
    "stories.ts": "_file_storybook",
    "stories.tsx": "_file_storybook",
    "story.js": "_file_storybook",
    "story.jsx": "_file_storybook",
    "story.ts": "_file_storybook",
    "story.tsx": "_file_storybook",
    "sty": "_file_tex",
    "styl": "_file_stylus",
    "sublime-commands": "_file_sublime",
    "sublime-menu": "_file_sublime",
    "sublime-settings": "_file_sublime",
    "sublime-theme": "_file_sublime",
    "sui": "_file_font",
    "suit": "_file_font",
    "suo": "_file_visualstudio",
    "swc": "_file_swc",
    "swf": "_file_flash",
    "swift": "_file_swift",
    "swig": "_file_swig",
    "tcsh": "_file_console",
    "tex": "_file_tex",
    "tfvars": "_file_terraform",
    "tfstate": "_file_terraform",
    "tfstate.backup": "_file_terraform",
    "tgz": "_file_zip",
    "tif": "_file_image",
    "tiff": "_file_image",
    "tmcolor": "_file_markup",
    "tmLanguage": "_file_xml",
    "tmTheme": "_file_markup",
    "todo": "_file_todo",
    "ttc": "_file_font",
    "twig": "_file_twig",
    "txt": "_file_document",
    "url": "_file_url",
    "v": "_file_vlang",
    "vb": "_file_visualstudio",
    "vbox-prev": "_file_virtual",
    "vbox": "_file_virtual",
    "vdi": "_file_virtual",
    "vob": "_file_movie",
    "vscodeignore": "_file_visualstudio",
    "vsh": "_file_vlang",
    "vsixmanifest": "_file_visualstudio",
    "webm": "_file_movie",
    "wim": "_file_zip",
    "wma": "_file_audio",
    "wmv": "_file_movie",
    "woff2": "_file_font",
    "xaml": "_file_xaml",
    "xls": "_file_table",
    "xlsx": "_file_table",
    "xquery": "_file_xml",
    "xsd": "_file_xml",
    "xsl": "_file_xml",
    "xslt": "_file_xml",
    "xz": "_file_zip",
    "YAML-tmLanguage": "_file_yaml",
    "yuv": "_file_movie",
    "zep": "_file_zephyr",
    "zig": "_file_zig",
    "zig.zon": "_file_zig",
    "ecr": "_file_crystal",
    "cr": "_file_crystal",
    "slang": "_file_crystal",
    "odin": "_file_odin",
    "trigger": "_file_salesforce",
    "nix": "_file_nix",
    "vhdl": "_file_vhdl",
    "wakatime": "_file_wakatime",
    "slurm": "_file_slurm",
    "sbatch": "_file_slurm",

    "blade": "blade",
    "blade.php": "blade",
    "blade.phtml": "blade",
    "spec.ts": "test-ts",
    "spec.cts": "test-ts",
    "spec.mts": "test-ts",
    "cy.ts": "test-ts",
    "e2e-spec.ts": "test-ts",
    "e2e-spec.cts": "test-ts",
    "e2e-spec.mts": "test-ts",
    "test.ts": "test-ts",
    "test.cts": "test-ts",
    "test.mts": "test-ts",
    "ts.snap": "test-ts",
    "spec-d.ts": "test-ts",
    "test-d.ts": "test-ts",
    "spec.tsx": "test-jsx",
    "test.tsx": "test-jsx",
    "tsx.snap": "test-jsx",
    "spec.jsx": "test-jsx",
    "test.jsx": "test-jsx",
    "jsx.snap": "test-jsx",
    "cy.jsx": "test-jsx",
    "cy.tsx": "test-jsx",
    "spec-d.tsx": "test-jsx",
    "test-d.tsx": "test-jsx",
    "spec.js": "test-js",
    "spec.cjs": "test-js",
    "spec.mjs": "test-js",
    "e2e-spec.js": "test-js",
    "e2e-spec.cjs": "test-js",
    "e2e-spec.mjs": "test-js",
    "test.js": "test-js",
    "test.cjs": "test-js",
    "test.mjs": "test-js",
    "js.snap": "test-js",
    "cy.js": "test-js",
    "cer": "certificate",
    "cert": "certificate",
    "crt": "certificate",
    "jl": "_file_julia",
    "graphql": "_file_graphql",
    "gql": "_file_graphql",
    "lib": "lib",
    "bib": "lib",
    "cfml": "coldfusion",
    "cfc": "coldfusion",
    "lucee": "coldfusion",
    "cfm": "coldfusion",
    "css": "file_css",
    "erb": "file_erb",
    "scss": "file_scss",
    "sass": "file_scss",
    "kt": "file_kotlin",
    "json": "file_json",
    "html": "file_html",
    "jsx": "file_react",
    "tsx": "file_react",
    "rake": "file_rake",
    "rb": "file_ruby",
    "less": "file_less",
    "js": "file_javascript",
    "cjs": "file_javascript",
    "mjs": "file_javascript",
    "ts": "file_typescript",
    "cts": "file_typescript",
    "mts": "file_typescript",
    "csv": "file_csv",
    "vue": "file_vue",
    "png": "file_image",
    "webp": "file_image",
    "jpg": "file_image",
    "jpeg": "file_image",
    "gif": "file_image",
    "ico": "file_image",
    "svg": "file_image",
    "ttf": "file_font",
    "woff": "file_font",
    "oft": "file_font",
    "eot": "file_font",
    "yaml": "file_yaml",
    "yml": "file_yaml",
    "java": "file_java",
    "xml": "file_xml",
    "sql": "file_sql",
    "md": "file_markdown",
    "properties": "file_properties",
    "sh": "file_shell",
    "zsh": "file_shell",
    "bash": "file_shell",
    "h": "file_h",
    "hh": "file_h",
    "hpp": "file_h",
    "hxx": "file_h",
    "c": "file_c",
    "cc": "file_cpp",
    "cpp": "file_cpp",
    "cxx": "file_cpp",
    "scala": "file_scala",
    "gz": "file_archive",
    "zip": "file_archive",
    "rar": "file_archive",
    "7z": "file_archive",
    "tar": "file_archive",
    "toml": "file_toml",
    "py": "file_python",
    "tf": "file_terraform",
    "go": "file_go",
    "http": "file_http",
    "rest": "file_http",
    "as": "file_actionscript",
    "php": "file_php",
    "cfg": "file_config",
    "conf": "file_config",
    "cnf": "file_config",
    "svelte": "file_svelte",
    "slim": "file_slim",
    "rs": "file_rust",
    "cs": "file_cs",
    "cshtml": "file_cshtml",
    "csproj": "file_csproj",
    "ejs": "file_ejs",
    "log": "file_log",
    "cmd": "file_shell",
    "ps1": "file_ps1",
    "prisma": "file_prisma"
  }
}
